hyperactive/__init__.py
hyperactive/_registry/__init__.py
hyperactive/_registry/_lookup.py
hyperactive/base/__init__.py
hyperactive/base/_experiment.py
hyperactive/base/_optimizer.py
hyperactive/base/tests/__init__.py
hyperactive/base/tests/test_dynamic_exp.py
hyperactive/base/tests/test_endtoend.py
hyperactive/experiment/__init__.py
hyperactive/experiment/func.py
hyperactive/experiment/bench/__init__.py
hyperactive/experiment/bench/_ackley.py
hyperactive/experiment/bench/_parabola.py
hyperactive/experiment/bench/_sphere.py
hyperactive/experiment/integrations/__init__.py
hyperactive/experiment/integrations/_skl_cv.py
hyperactive/experiment/integrations/_skl_metrics.py
hyperactive/experiment/integrations/sklearn_cv.py
hyperactive/experiment/integrations/skpro_probareg.py
hyperactive/experiment/integrations/sktime_classification.py
hyperactive/experiment/integrations/sktime_forecasting.py
hyperactive/experiment/integrations/torch_lightning_experiment.py
hyperactive/integrations/__init__.py
hyperactive/integrations/sklearn/__init__.py
hyperactive/integrations/sklearn/_compat.py
hyperactive/integrations/sklearn/best_estimator.py
hyperactive/integrations/sklearn/checks.py
hyperactive/integrations/sklearn/opt_cv.py
hyperactive/integrations/sklearn/utils.py
hyperactive/integrations/sklearn/tests/__init__.py
hyperactive/integrations/sklearn/tests/test_parametrize_with_checks.py
hyperactive/integrations/skpro/__init__.py
hyperactive/integrations/skpro/_probareg.py
hyperactive/integrations/skpro/tests/__init__.py
hyperactive/integrations/skpro/tests/test_skpro_estimators.py
hyperactive/integrations/sktime/__init__.py
hyperactive/integrations/sktime/_classification.py
hyperactive/integrations/sktime/_forecasting.py
hyperactive/integrations/sktime/tests/__init__.py
hyperactive/integrations/sktime/tests/test_sktime_estimators.py
hyperactive/opt/__init__.py
hyperactive/opt/_common.py
hyperactive/opt/random_search.py
hyperactive/opt/_adapters/__init__.py
hyperactive-5.0.3.dist-info/licenses/LICENSE
hyperactive-5.0.3.dist-info/METADATA
hyperactive-5.0.3.dist-info/WHEEL
hyperactive-5.0.3.dist-info/top_level.txt
hyperactive-5.0.3.dist-info/RECORD
