Metadata-Version: 2.4
Name: hyperactive
Version: 5.0.3
Summary: An optimization and data collection toolbox for convenient and fast prototyping of computationally expensive models.
Author-email: Simon Blanke <simon.blanke@yahoo.com>
Maintainer-email: Simon Blanke <simon.blanke@yahoo.com>
License: MIT License
Project-URL: Homepage, https://github.com/SimonBlanke/Hyperactive
Project-URL: Bug Reports, https://github.com/SimonBlanke/Hyperactive/issues
Project-URL: Source, https://github.com/SimonBlanke/Hyperactive/
Keywords: optimization,hyperparameter-tuning,bayesian-optimization,machine-learning,data-science,hyperparameter-optimization,automl,model-selection,gradient-free,black-box-optimization,scikit-learn,pytorch
Classifier: Programming Language :: Python :: 3
Classifier: Programming Language :: Python :: 3.10
Classifier: Programming Language :: Python :: 3.11
Classifier: Programming Language :: Python :: 3.12
Classifier: Programming Language :: Python :: 3.13
Classifier: Programming Language :: Python :: 3.14
Classifier: License :: OSI Approved :: MIT License
Classifier: Operating System :: OS Independent
Classifier: Topic :: Scientific/Engineering :: Information Analysis
Classifier: Topic :: Scientific/Engineering :: Mathematics
Classifier: Topic :: Scientific/Engineering :: Artificial Intelligence
Classifier: Topic :: Software Development :: Libraries :: Python Modules
Classifier: Development Status :: 5 - Production/Stable
Classifier: Intended Audience :: Developers
Classifier: Intended Audience :: Information Technology
Classifier: Intended Audience :: Science/Research
Classifier: Intended Audience :: Education
Requires-Python: >=3.10
License-File: LICENSE
Requires-Dist: numpy<3.0.0,>=1.18.1
Requires-Dist: tqdm<5.0.0,>=4.48.0
Requires-Dist: pandas<3.0.0
Requires-Dist: gradient-free-optimizers<2.0.0,>=1.2.4
Requires-Dist: scikit-base<1.0.0
Requires-Dist: scikit-learn<1.8.0
Provides-Extra: sklearn-integration
Requires-Dist: scikit-learn<1.8.0; extra == "sklearn-integration"
Provides-Extra: sktime-integration
Requires-Dist: skpro; extra == "sktime-integration"
Requires-Dist: sktime; python_version < "3.14" and extra == "sktime-integration"
Provides-Extra: build
Requires-Dist: setuptools; extra == "build"
Requires-Dist: build; extra == "build"
Requires-Dist: wheel; extra == "build"
Provides-Extra: test
Requires-Dist: pytest==9.0.2; extra == "test"
Requires-Dist: flake8; extra == "test"
Requires-Dist: pytest-cov; extra == "test"
Requires-Dist: pathos; extra == "test"
Requires-Dist: torch; python_version < "3.14" and extra == "test"
Requires-Dist: tf_keras; extra == "test"
Provides-Extra: test-parallel-backends
Requires-Dist: dask; extra == "test-parallel-backends"
Requires-Dist: joblib; extra == "test-parallel-backends"
Requires-Dist: ray>=2.40.0; python_version < "3.13" and extra == "test-parallel-backends"
Provides-Extra: docs
Requires-Dist: myst-parser; extra == "docs"
Requires-Dist: numpydoc; extra == "docs"
Requires-Dist: pydata-sphinx-theme; extra == "docs"
Requires-Dist: Sphinx<9.0.0,>=7.0.0; extra == "docs"
Requires-Dist: sphinx-copybutton; extra == "docs"
Requires-Dist: sphinx-design; extra == "docs"
Requires-Dist: sphinx-issues; extra == "docs"
Provides-Extra: all-extras
Requires-Dist: hyperactive[integrations]; extra == "all-extras"
Requires-Dist: optuna<5; extra == "all-extras"
Requires-Dist: cmaes; extra == "all-extras"
Requires-Dist: lightning; extra == "all-extras"
Dynamic: license-file
